lmxy/__init__.py
lmxy/_env.py
lmxy/_nodes.py
lmxy/_parsers.py
lmxy/_queue.py
lmxy/_responses.py
lmxy/_types.py
lmxy/bert_score.py
lmxy/embed.py
lmxy/fastembed.py
lmxy/openailike.py
lmxy/py.typed
lmxy/qdrant.py
lmxy/rerank.py
lmxy/tokenizer.py
lmxy/util.py
lmxy-0.3.7.dist-info/METADATA
lmxy-0.3.7.dist-info/WHEEL
lmxy-0.3.7.dist-info/licenses/LICENSE
lmxy-0.3.7.dist-info/RECORD
