Metadata-Version: 2.4
Name: lmxy
Version: 0.3.7
Summary: Language models extensions
Project-URL: homepage, https://github.com/arquolo/lmx
Author-email: Paul Maevskikh <arquolo@gmail.com>
Maintainer-email: Paul Maevskikh <arquolo@gmail.com>
License: MIT License
License-File: LICENSE
Classifier: Development Status :: 3 - Alpha
Classifier: License :: OSI Approved :: MIT License
Classifier: Operating System :: OS Independent
Classifier: Programming Language :: Python :: 3
Classifier: Programming Language :: Python :: 3.12
Classifier: Programming Language :: Python :: 3.13
Requires-Python: >=3.12
Requires-Dist: glow~=0.15.4
Requires-Dist: httpx
Requires-Dist: pydantic-settings
Requires-Dist: pydantic~=2.10
Requires-Dist: tenacity
Provides-Extra: all
Requires-Dist: fastembed~=0.7.0; extra == 'all'
Requires-Dist: grpcio; extra == 'all'
Requires-Dist: llama-index-core<0.15,>=0.13.0; extra == 'all'
Requires-Dist: llama-index-utils-huggingface; extra == 'all'
Requires-Dist: openai~=1.102; extra == 'all'
Requires-Dist: orjson; extra == 'all'
Requires-Dist: qdrant-client~=1.15.1; extra == 'all'
Requires-Dist: tiktoken; extra == 'all'
Requires-Dist: transformers; extra == 'all'
Provides-Extra: base
Requires-Dist: llama-index-core<0.15,>=0.13.0; extra == 'base'
Requires-Dist: llama-index-utils-huggingface; extra == 'base'
Provides-Extra: bert-score
Requires-Dist: torch>=2.0; extra == 'bert-score'
Requires-Dist: tqdm; extra == 'bert-score'
Requires-Dist: transformers~=4.0; extra == 'bert-score'
Provides-Extra: dev
Requires-Dist: black~=25.1; extra == 'dev'
Requires-Dist: flake8-alphabetize; extra == 'dev'
Requires-Dist: flake8-pie; extra == 'dev'
Requires-Dist: flake8-pyi; extra == 'dev'
Requires-Dist: flake8-pyproject; extra == 'dev'
Requires-Dist: flake8-simplify; extra == 'dev'
Requires-Dist: flake8~=7.0; extra == 'dev'
Requires-Dist: isort; extra == 'dev'
Requires-Dist: mypy~=1.18; extra == 'dev'
Requires-Dist: pytest-asyncio; extra == 'dev'
Requires-Dist: pytest~=8.0; extra == 'dev'
Requires-Dist: ruff~=0.13.2; extra == 'dev'
Requires-Dist: types-requests; extra == 'dev'
Provides-Extra: dev-core
Requires-Dist: black~=25.1; extra == 'dev-core'
Requires-Dist: flake8-pie; extra == 'dev-core'
Requires-Dist: flake8-pyi; extra == 'dev-core'
Requires-Dist: flake8-pyproject; extra == 'dev-core'
Requires-Dist: flake8-simplify; extra == 'dev-core'
Requires-Dist: flake8~=7.0; extra == 'dev-core'
Requires-Dist: isort; extra == 'dev-core'
Requires-Dist: mypy~=1.18; extra == 'dev-core'
Requires-Dist: pytest-asyncio; extra == 'dev-core'
Requires-Dist: pytest~=8.0; extra == 'dev-core'
Requires-Dist: ruff~=0.13.2; extra == 'dev-core'
Requires-Dist: types-requests; extra == 'dev-core'
Provides-Extra: dev-wemake
Requires-Dist: black~=25.1; extra == 'dev-wemake'
Requires-Dist: flake8-pie; extra == 'dev-wemake'
Requires-Dist: flake8-pyi; extra == 'dev-wemake'
Requires-Dist: flake8-pyproject; extra == 'dev-wemake'
Requires-Dist: flake8-simplify; extra == 'dev-wemake'
Requires-Dist: flake8~=7.0; extra == 'dev-wemake'
Requires-Dist: isort; extra == 'dev-wemake'
Requires-Dist: mypy~=1.18; extra == 'dev-wemake'
Requires-Dist: pytest-asyncio; extra == 'dev-wemake'
Requires-Dist: pytest~=8.0; extra == 'dev-wemake'
Requires-Dist: ruff~=0.13.2; extra == 'dev-wemake'
Requires-Dist: types-requests; extra == 'dev-wemake'
Requires-Dist: wemake-python-styleguide~=1.3.0; extra == 'dev-wemake'
Provides-Extra: fastembed
Requires-Dist: fastembed~=0.7.0; extra == 'fastembed'
Provides-Extra: openailike
Requires-Dist: llama-index-core<0.15,>=0.13.0; extra == 'openailike'
Requires-Dist: llama-index-utils-huggingface; extra == 'openailike'
Requires-Dist: openai~=1.102; extra == 'openailike'
Requires-Dist: tiktoken; extra == 'openailike'
Requires-Dist: transformers; extra == 'openailike'
Provides-Extra: qdrant
Requires-Dist: fastembed~=0.7.0; extra == 'qdrant'
Requires-Dist: grpcio; extra == 'qdrant'
Requires-Dist: llama-index-core<0.15,>=0.13.0; extra == 'qdrant'
Requires-Dist: llama-index-utils-huggingface; extra == 'qdrant'
Requires-Dist: orjson; extra == 'qdrant'
Requires-Dist: qdrant-client~=1.15.1; extra == 'qdrant'
Provides-Extra: tokenizer
Requires-Dist: tiktoken; extra == 'tokenizer'
Requires-Dist: transformers; extra == 'tokenizer'
